arachnio/__init__.py
arachnio/client.py
arachnio-0.0.0.dist-info/LICENSE
arachnio-0.0.0.dist-info/METADATA
arachnio-0.0.0.dist-info/WHEEL
arachnio-0.0.0.dist-info/top_level.txt
arachnio-0.0.0.dist-info/RECORD
