Metadata-Version: 2.1
Name: arachnio
Version: 0.0.0
Summary: Client library for interacting with Arachnio API
Author-email: Andy Boothe <andy@arachn.io>
License: Apache License
Project-URL: Homepage, https://github.com/arachnio/arachnio4py
Keywords: arachnio,arachn.io
Classifier: License :: OSI Approved :: Apache Software License
Classifier: Programming Language :: Python
Classifier: Programming Language :: Python :: 3
Requires-Python: >=3.9
License-File: LICENSE
Requires-Dist: requests (~=2.28.2)
Requires-Dist: tomli ; python_version < "3.11"
